<?xml version="1.0" encoding="UTF-8" standalone="no"?>
<DIAGRAMA ID="1" TIPO="tpConceitual" UniversalUnicID="D5F5-D7-DE48-E6-68DF-A1-81">
    <InfoDiagrama ID="1">
        <Versao Valor="3.2.0"/>
        <Autores/>
        <Observacao/>
        <Width Valor="4096"/>
        <Height Valor="4096"/>
        <Alinhamento_v Valor="50"/>
        <Alinhamento_h Valor="60"/>
        <Zoom Valor="75"/>
        <Fonte Estilo="1" Nome="Arial" Tamanho="12"/>
        <Localizacao Left="54" Top="47"/>
        <Realce Valor="false"/>
    </InfoDiagrama>
    <Entidade ID="2">
        <Bounds Height="58" Left="370" Top="150" Width="120"/>
        <DisablePainted Valor="false"/>
        <Texto>Pessoa</Texto>
        <Observacao/>
        <Dicionario/>
        <Fonte Estilo="1" Nome="Arial" Tamanho="12"/>
        <Ancorado Valor="false"/>
        <AtributosOcultos Valor=""/>
    </Entidade>
    <Atributo ID="3">
        <Bounds Height="14" Left="394" Top="59" Width="41"/>
        <DisablePainted Valor="false"/>
        <Texto>cpf</Texto>
        <Observacao/>
        <Dicionario/>
        <Fonte Estilo="1" Nome="Arial" Tamanho="12"/>
        <Ancorado Valor="false"/>
        <DirecaoFromInspector Valor="0"/>
        <Autosize Valor="true"/>
        <Identificador Valor="true"/>
        <Opcional Valor="false"/>
        <Multivalorado Valor="false"/>
        <CardMinFromString Valor="1"/>
        <CardMaxFromString Valor="n"/>
        <TipoAtributo Valor=""/>
    </Atributo>
    <Ligacao ID="4">
        <DisablePainted Valor="false"/>
        <Tag LinhaMestre="-1"/>
        <Dashed Valor="false"/>
        <Ancorado Valor="false"/>
        <TemSetaPontaA Valor="false"/>
        <TemSetaPontaB Valor="false"/>
        <SetaAberta Valor="true"/>
        <SetaLargura Valor="10"/>
        <Inteligente Valor="true"/>
        <Largura Valor="1"/>
        <Ligacoes PontaA="3" PontaB="2"/>
        <Pontos>
            <Ponto Left="390" Top="63"/>
            <Ponto Left="381" Top="63"/>
            <Ponto Left="381" Top="108"/>
            <Ponto Left="381" Top="108"/>
            <Ponto Left="381" Top="146"/>
        </Pontos>
    </Ligacao>
    <Atributo ID="5">
        <Bounds Height="14" Left="408" Top="78" Width="35"/>
        <DisablePainted Valor="false"/>
        <Texto>rg</Texto>
        <Observacao/>
        <Dicionario/>
        <Fonte Estilo="1" Nome="Arial" Tamanho="12"/>
        <Ancorado Valor="false"/>
        <DirecaoFromInspector Valor="0"/>
        <Autosize Valor="true"/>
        <Identificador Valor="false"/>
        <Opcional Valor="false"/>
        <Multivalorado Valor="false"/>
        <CardMinFromString Valor="1"/>
        <CardMaxFromString Valor="n"/>
        <TipoAtributo Valor=""/>
    </Atributo>
    <Ligacao ID="6">
        <DisablePainted Valor="false"/>
        <Tag LinhaMestre="-1"/>
        <Dashed Valor="false"/>
        <Ancorado Valor="false"/>
        <TemSetaPontaA Valor="false"/>
        <TemSetaPontaB Valor="false"/>
        <SetaAberta Valor="true"/>
        <SetaLargura Valor="10"/>
        <Inteligente Valor="true"/>
        <Largura Valor="1"/>
        <Ligacoes PontaA="5" PontaB="2"/>
        <Pontos>
            <Ponto Left="404" Top="82"/>
            <Ponto Left="395" Top="82"/>
            <Ponto Left="395" Top="118"/>
            <Ponto Left="395" Top="118"/>
            <Ponto Left="395" Top="146"/>
        </Pontos>
    </Ligacao>
    <Atributo ID="7">
        <Bounds Height="14" Left="422" Top="97" Width="78"/>
        <DisablePainted Valor="false"/>
        <Texto>endereço</Texto>
        <Observacao/>
        <Dicionario/>
        <Fonte Estilo="1" Nome="Arial" Tamanho="12"/>
        <Ancorado Valor="false"/>
        <DirecaoFromInspector Valor="0"/>
        <Autosize Valor="true"/>
        <Identificador Valor="false"/>
        <Opcional Valor="false"/>
        <Multivalorado Valor="false"/>
        <CardMinFromString Valor="1"/>
        <CardMaxFromString Valor="n"/>
        <TipoAtributo Valor=""/>
    </Atributo>
    <Ligacao ID="8">
        <DisablePainted Valor="false"/>
        <Tag LinhaMestre="-1"/>
        <Dashed Valor="false"/>
        <Ancorado Valor="false"/>
        <TemSetaPontaA Valor="false"/>
        <TemSetaPontaB Valor="false"/>
        <SetaAberta Valor="true"/>
        <SetaLargura Valor="10"/>
        <Inteligente Valor="true"/>
        <Largura Valor="1"/>
        <Ligacoes PontaA="7" PontaB="2"/>
        <Pontos>
            <Ponto Left="418" Top="101"/>
            <Ponto Left="409" Top="101"/>
            <Ponto Left="409" Top="127"/>
            <Ponto Left="409" Top="127"/>
            <Ponto Left="409" Top="146"/>
        </Pontos>
    </Ligacao>
    <Atributo ID="9">
        <Bounds Height="14" Left="436" Top="116" Width="139"/>
        <DisablePainted Valor="false"/>
        <Texto>data de nascimento</Texto>
        <Observacao/>
        <Dicionario/>
        <Fonte Estilo="1" Nome="Arial" Tamanho="12"/>
        <Ancorado Valor="false"/>
        <DirecaoFromInspector Valor="0"/>
        <Autosize Valor="true"/>
        <Identificador Valor="false"/>
        <Opcional Valor="false"/>
        <Multivalorado Valor="false"/>
        <CardMinFromString Valor="1"/>
        <CardMaxFromString Valor="n"/>
        <TipoAtributo Valor=""/>
    </Atributo>
    <Ligacao ID="10">
        <DisablePainted Valor="false"/>
        <Tag LinhaMestre="-1"/>
        <Dashed Valor="false"/>
        <Ancorado Valor="false"/>
        <TemSetaPontaA Valor="false"/>
        <TemSetaPontaB Valor="false"/>
        <SetaAberta Valor="true"/>
        <SetaLargura Valor="10"/>
        <Inteligente Valor="true"/>
        <Largura Valor="1"/>
        <Ligacoes PontaA="9" PontaB="2"/>
        <Pontos>
            <Ponto Left="432" Top="120"/>
            <Ponto Left="423" Top="120"/>
            <Ponto Left="423" Top="137"/>
            <Ponto Left="423" Top="137"/>
            <Ponto Left="423" Top="146"/>
        </Pontos>
    </Ligacao>
    <Especializacao ID="18">
        <Bounds Height="32" Left="410" Top="269" Width="40"/>
        <DisablePainted Valor="false"/>
        <Texto>Especialização_1</Texto>
        <Observacao/>
        <Dicionario/>
        <Fonte Estilo="1" Nome="Arial" Tamanho="12"/>
        <Ancorado Valor="false"/>
        <Direcao Valor="0"/>
        <Ocupado01 ID="18"/>
        <Ocupado02 ID="18"/>
        <Ocupado03 ID="18"/>
        <Parcial Valor="false"/>
    </Especializacao>
    <Ligacao ID="20">
        <DisablePainted Valor="false"/>
        <Tag LinhaMestre="-1"/>
        <Dashed Valor="false"/>
        <Ancorado Valor="false"/>
        <TemSetaPontaA Valor="false"/>
        <TemSetaPontaB Valor="false"/>
        <SetaAberta Valor="true"/>
        <SetaLargura Valor="10"/>
        <Inteligente Valor="false"/>
        <Largura Valor="1"/>
        <Ligacoes PontaA="18" PontaB="2"/>
        <Pontos>
            <Ponto Left="427" Top="266"/>
            <Ponto Left="428" Top="205"/>
        </Pontos>
    </Ligacao>
    <Entidade ID="24">
        <Bounds Height="58" Left="151" Top="386" Width="120"/>
        <DisablePainted Valor="false"/>
        <Texto>Atendente</Texto>
        <Observacao/>
        <Dicionario/>
        <Fonte Estilo="1" Nome="Arial" Tamanho="12"/>
        <Ancorado Valor="false"/>
        <AtributosOcultos Valor=""/>
    </Entidade>
    <Atributo ID="25">
        <Bounds Height="14" Left="175" Top="352" Width="127"/>
        <DisablePainted Valor="false"/>
        <Texto>formação_escolar</Texto>
        <Observacao/>
        <Dicionario/>
        <Fonte Estilo="1" Nome="Arial" Tamanho="12"/>
        <Ancorado Valor="false"/>
        <DirecaoFromInspector Valor="0"/>
        <Autosize Valor="true"/>
        <Identificador Valor="false"/>
        <Opcional Valor="false"/>
        <Multivalorado Valor="false"/>
        <CardMinFromString Valor="1"/>
        <CardMaxFromString Valor="n"/>
        <TipoAtributo Valor=""/>
    </Atributo>
    <Ligacao ID="26">
        <DisablePainted Valor="false"/>
        <Tag LinhaMestre="-1"/>
        <Dashed Valor="false"/>
        <Ancorado Valor="false"/>
        <TemSetaPontaA Valor="false"/>
        <TemSetaPontaB Valor="false"/>
        <SetaAberta Valor="true"/>
        <SetaLargura Valor="10"/>
        <Inteligente Valor="true"/>
        <Largura Valor="1"/>
        <Ligacoes PontaA="25" PontaB="24"/>
        <Pontos>
            <Ponto Left="172" Top="356"/>
            <Ponto Left="162" Top="356"/>
            <Ponto Left="162" Top="382"/>
        </Pontos>
    </Ligacao>
    <Ligacao ID="28">
        <DisablePainted Valor="false"/>
        <Tag LinhaMestre="-1"/>
        <Dashed Valor="false"/>
        <Ancorado Valor="false"/>
        <TemSetaPontaA Valor="false"/>
        <TemSetaPontaB Valor="false"/>
        <SetaAberta Valor="true"/>
        <SetaLargura Valor="10"/>
        <Inteligente Valor="false"/>
        <Largura Valor="1"/>
        <Ligacoes PontaA="18" PontaB="24"/>
        <Pontos>
            <Ponto Left="407" Top="298"/>
            <Ponto Left="268" Top="386"/>
        </Pontos>
    </Ligacao>
    <Entidade ID="30">
        <Bounds Height="58" Left="370" Top="387" Width="120"/>
        <DisablePainted Valor="false"/>
        <Texto>Passageiro</Texto>
        <Observacao/>
        <Dicionario/>
        <Fonte Estilo="1" Nome="Arial" Tamanho="12"/>
        <Ancorado Valor="false"/>
        <AtributosOcultos Valor=""/>
    </Entidade>
    <Ligacao ID="33">
        <DisablePainted Valor="false"/>
        <Tag LinhaMestre="-1"/>
        <Dashed Valor="false"/>
        <Ancorado Valor="false"/>
        <TemSetaPontaA Valor="false"/>
        <TemSetaPontaB Valor="false"/>
        <SetaAberta Valor="true"/>
        <SetaLargura Valor="10"/>
        <Inteligente Valor="false"/>
        <Largura Valor="1"/>
        <Ligacoes PontaA="30" PontaB="18"/>
        <Pontos>
            <Ponto Left="427" Top="383"/>
            <Ponto Left="427" Top="298"/>
        </Pontos>
    </Ligacao>
    <Atributo ID="36">
        <Bounds Height="14" Left="327" Top="353" Width="93"/>
        <DisablePainted Valor="false"/>
        <Texto>nro_crédito</Texto>
        <Observacao/>
        <Dicionario/>
        <Fonte Estilo="1" Nome="Arial" Tamanho="12"/>
        <Ancorado Valor="false"/>
        <DirecaoFromInspector Valor="1"/>
        <Autosize Valor="true"/>
        <Identificador Valor="false"/>
        <Opcional Valor="false"/>
        <Multivalorado Valor="false"/>
        <CardMinFromString Valor="1"/>
        <CardMaxFromString Valor="n"/>
        <TipoAtributo Valor=""/>
    </Atributo>
    <Ligacao ID="37">
        <DisablePainted Valor="false"/>
        <Tag LinhaMestre="-1"/>
        <Dashed Valor="false"/>
        <Ancorado Valor="false"/>
        <TemSetaPontaA Valor="false"/>
        <TemSetaPontaB Valor="false"/>
        <SetaAberta Valor="true"/>
        <SetaLargura Valor="10"/>
        <Inteligente Valor="true"/>
        <Largura Valor="1"/>
        <Ligacoes PontaA="36" PontaB="30"/>
        <Pontos>
            <Ponto Left="418" Top="357"/>
            <Ponto Left="427" Top="357"/>
            <Ponto Left="427" Top="374"/>
            <Ponto Left="395" Top="374"/>
            <Ponto Left="395" Top="383"/>
        </Pontos>
    </Ligacao>
    <Entidade ID="58">
        <Bounds Height="58" Left="600" Top="386" Width="120"/>
        <DisablePainted Valor="false"/>
        <Texto>Motorista</Texto>
        <Observacao/>
        <Dicionario/>
        <Fonte Estilo="1" Nome="Arial" Tamanho="12"/>
        <Ancorado Valor="false"/>
        <AtributosOcultos Valor=""/>
    </Entidade>
    <Atributo ID="59">
        <Bounds Height="14" Left="627" Top="333" Width="43"/>
        <DisablePainted Valor="false"/>
        <Texto>cnh</Texto>
        <Observacao/>
        <Dicionario/>
        <Fonte Estilo="1" Nome="Arial" Tamanho="12"/>
        <Ancorado Valor="false"/>
        <DirecaoFromInspector Valor="0"/>
        <Autosize Valor="true"/>
        <Identificador Valor="false"/>
        <Opcional Valor="false"/>
        <Multivalorado Valor="false"/>
        <CardMinFromString Valor="1"/>
        <CardMaxFromString Valor="n"/>
        <TipoAtributo Valor=""/>
    </Atributo>
    <Ligacao ID="60">
        <DisablePainted Valor="false"/>
        <Tag LinhaMestre="-1"/>
        <Dashed Valor="false"/>
        <Ancorado Valor="false"/>
        <TemSetaPontaA Valor="false"/>
        <TemSetaPontaB Valor="false"/>
        <SetaAberta Valor="true"/>
        <SetaLargura Valor="10"/>
        <Inteligente Valor="true"/>
        <Largura Valor="1"/>
        <Ligacoes PontaA="59" PontaB="58"/>
        <Pontos>
            <Ponto Left="624" Top="337"/>
            <Ponto Left="611" Top="337"/>
            <Ponto Left="611" Top="382"/>
        </Pontos>
    </Ligacao>
    <Atributo ID="61">
        <Bounds Height="14" Left="641" Top="352" Width="113"/>
        <DisablePainted Valor="false"/>
        <Texto>conta_corrente</Texto>
        <Observacao/>
        <Dicionario/>
        <Fonte Estilo="1" Nome="Arial" Tamanho="12"/>
        <Ancorado Valor="false"/>
        <DirecaoFromInspector Valor="0"/>
        <Autosize Valor="true"/>
        <Identificador Valor="false"/>
        <Opcional Valor="false"/>
        <Multivalorado Valor="false"/>
        <CardMinFromString Valor="1"/>
        <CardMaxFromString Valor="n"/>
        <TipoAtributo Valor=""/>
    </Atributo>
    <Ligacao ID="62">
        <DisablePainted Valor="false"/>
        <Tag LinhaMestre="-1"/>
        <Dashed Valor="false"/>
        <Ancorado Valor="false"/>
        <TemSetaPontaA Valor="false"/>
        <TemSetaPontaB Valor="false"/>
        <SetaAberta Valor="true"/>
        <SetaLargura Valor="10"/>
        <Inteligente Valor="true"/>
        <Largura Valor="1"/>
        <Ligacoes PontaA="61" PontaB="58"/>
        <Pontos>
            <Ponto Left="637" Top="356"/>
            <Ponto Left="625" Top="356"/>
            <Ponto Left="625" Top="382"/>
        </Pontos>
    </Ligacao>
    <Ligacao ID="64">
        <DisablePainted Valor="false"/>
        <Tag LinhaMestre="-1"/>
        <Dashed Valor="false"/>
        <Ancorado Valor="false"/>
        <TemSetaPontaA Valor="false"/>
        <TemSetaPontaB Valor="false"/>
        <SetaAberta Valor="true"/>
        <SetaLargura Valor="10"/>
        <Inteligente Valor="false"/>
        <Largura Valor="1"/>
        <Ligacoes PontaA="18" PontaB="58"/>
        <Pontos>
            <Ponto Left="447" Top="298"/>
            <Ponto Left="596" Top="384"/>
        </Pontos>
    </Ligacao>
    <Entidade ID="79">
        <Bounds Height="58" Left="1054" Top="387" Width="120"/>
        <DisablePainted Valor="false"/>
        <Texto>Veículo</Texto>
        <Observacao/>
        <Dicionario/>
        <Fonte Estilo="1" Nome="Arial" Tamanho="12"/>
        <Ancorado Valor="false"/>
        <AtributosOcultos Valor=""/>
    </Entidade>
    <Atributo ID="94">
        <Bounds Height="14" Left="1078" Top="220" Width="73"/>
        <DisablePainted Valor="false"/>
        <Texto>renavam</Texto>
        <Observacao/>
        <Dicionario/>
        <Fonte Estilo="1" Nome="Arial" Tamanho="12"/>
        <Ancorado Valor="false"/>
        <DirecaoFromInspector Valor="0"/>
        <Autosize Valor="true"/>
        <Identificador Valor="true"/>
        <Opcional Valor="false"/>
        <Multivalorado Valor="false"/>
        <CardMinFromString Valor="1"/>
        <CardMaxFromString Valor="n"/>
        <TipoAtributo Valor=""/>
    </Atributo>
    <Ligacao ID="95">
        <DisablePainted Valor="false"/>
        <Tag LinhaMestre="-1"/>
        <Dashed Valor="false"/>
        <Ancorado Valor="false"/>
        <TemSetaPontaA Valor="false"/>
        <TemSetaPontaB Valor="false"/>
        <SetaAberta Valor="true"/>
        <SetaLargura Valor="10"/>
        <Inteligente Valor="true"/>
        <Largura Valor="1"/>
        <Ligacoes PontaA="94" PontaB="79"/>
        <Pontos>
            <Ponto Left="1075" Top="224"/>
            <Ponto Left="1065" Top="224"/>
            <Ponto Left="1065" Top="383"/>
        </Pontos>
    </Ligacao>
    <Atributo ID="96">
        <Bounds Height="14" Left="1092" Top="239" Width="58"/>
        <DisablePainted Valor="false"/>
        <Texto>marca</Texto>
        <Observacao/>
        <Dicionario/>
        <Fonte Estilo="1" Nome="Arial" Tamanho="12"/>
        <Ancorado Valor="false"/>
        <DirecaoFromInspector Valor="0"/>
        <Autosize Valor="true"/>
        <Identificador Valor="false"/>
        <Opcional Valor="false"/>
        <Multivalorado Valor="false"/>
        <CardMinFromString Valor="1"/>
        <CardMaxFromString Valor="n"/>
        <TipoAtributo Valor=""/>
    </Atributo>
    <Ligacao ID="97">
        <DisablePainted Valor="false"/>
        <Tag LinhaMestre="-1"/>
        <Dashed Valor="false"/>
        <Ancorado Valor="false"/>
        <TemSetaPontaA Valor="false"/>
        <TemSetaPontaB Valor="false"/>
        <SetaAberta Valor="true"/>
        <SetaLargura Valor="10"/>
        <Inteligente Valor="true"/>
        <Largura Valor="1"/>
        <Ligacoes PontaA="96" PontaB="79"/>
        <Pontos>
            <Ponto Left="1088" Top="243"/>
            <Ponto Left="1079" Top="243"/>
            <Ponto Left="1079" Top="317"/>
            <Ponto Left="1079" Top="317"/>
            <Ponto Left="1079" Top="383"/>
        </Pontos>
    </Ligacao>
    <Atributo ID="98">
        <Bounds Height="14" Left="1106" Top="258" Width="57"/>
        <DisablePainted Valor="false"/>
        <Texto>preço</Texto>
        <Observacao/>
        <Dicionario/>
        <Fonte Estilo="1" Nome="Arial" Tamanho="12"/>
        <Ancorado Valor="false"/>
        <DirecaoFromInspector Valor="0"/>
        <Autosize Valor="true"/>
        <Identificador Valor="false"/>
        <Opcional Valor="false"/>
        <Multivalorado Valor="false"/>
        <CardMinFromString Valor="1"/>
        <CardMaxFromString Valor="n"/>
        <TipoAtributo Valor=""/>
    </Atributo>
    <Ligacao ID="99">
        <DisablePainted Valor="false"/>
        <Tag LinhaMestre="-1"/>
        <Dashed Valor="false"/>
        <Ancorado Valor="false"/>
        <TemSetaPontaA Valor="false"/>
        <TemSetaPontaB Valor="false"/>
        <SetaAberta Valor="true"/>
        <SetaLargura Valor="10"/>
        <Inteligente Valor="true"/>
        <Largura Valor="1"/>
        <Ligacoes PontaA="98" PontaB="79"/>
        <Pontos>
            <Ponto Left="1102" Top="262"/>
            <Ponto Left="1093" Top="262"/>
            <Ponto Left="1093" Top="326"/>
            <Ponto Left="1093" Top="326"/>
            <Ponto Left="1093" Top="383"/>
        </Pontos>
    </Ligacao>
    <Atributo ID="100">
        <Bounds Height="14" Left="1120" Top="277" Width="46"/>
        <DisablePainted Valor="false"/>
        <Texto>tipo</Texto>
        <Observacao/>
        <Dicionario/>
        <Fonte Estilo="1" Nome="Arial" Tamanho="12"/>
        <Ancorado Valor="false"/>
        <DirecaoFromInspector Valor="0"/>
        <Autosize Valor="true"/>
        <Identificador Valor="false"/>
        <Opcional Valor="false"/>
        <Multivalorado Valor="false"/>
        <CardMinFromString Valor="1"/>
        <CardMaxFromString Valor="n"/>
        <TipoAtributo Valor=""/>
    </Atributo>
    <Ligacao ID="101">
        <DisablePainted Valor="false"/>
        <Tag LinhaMestre="-1"/>
        <Dashed Valor="false"/>
        <Ancorado Valor="false"/>
        <TemSetaPontaA Valor="false"/>
        <TemSetaPontaB Valor="false"/>
        <SetaAberta Valor="true"/>
        <SetaLargura Valor="10"/>
        <Inteligente Valor="true"/>
        <Largura Valor="1"/>
        <Ligacoes PontaA="100" PontaB="79"/>
        <Pontos>
            <Ponto Left="1116" Top="281"/>
            <Ponto Left="1107" Top="281"/>
            <Ponto Left="1107" Top="336"/>
            <Ponto Left="1107" Top="336"/>
            <Ponto Left="1107" Top="383"/>
        </Pontos>
    </Ligacao>
    <Atributo ID="102">
        <Bounds Height="14" Left="1134" Top="296" Width="66"/>
        <DisablePainted Valor="false"/>
        <Texto>modelo</Texto>
        <Observacao/>
        <Dicionario/>
        <Fonte Estilo="1" Nome="Arial" Tamanho="12"/>
        <Ancorado Valor="false"/>
        <DirecaoFromInspector Valor="0"/>
        <Autosize Valor="true"/>
        <Identificador Valor="false"/>
        <Opcional Valor="false"/>
        <Multivalorado Valor="false"/>
        <CardMinFromString Valor="1"/>
        <CardMaxFromString Valor="n"/>
        <TipoAtributo Valor=""/>
    </Atributo>
    <Ligacao ID="103">
        <DisablePainted Valor="false"/>
        <Tag LinhaMestre="-1"/>
        <Dashed Valor="false"/>
        <Ancorado Valor="false"/>
        <TemSetaPontaA Valor="false"/>
        <TemSetaPontaB Valor="false"/>
        <SetaAberta Valor="true"/>
        <SetaLargura Valor="10"/>
        <Inteligente Valor="true"/>
        <Largura Valor="1"/>
        <Ligacoes PontaA="102" PontaB="79"/>
        <Pontos>
            <Ponto Left="1130" Top="300"/>
            <Ponto Left="1121" Top="300"/>
            <Ponto Left="1121" Top="345"/>
            <Ponto Left="1121" Top="345"/>
            <Ponto Left="1121" Top="383"/>
        </Pontos>
    </Ligacao>
    <Atributo ID="104">
        <Bounds Height="14" Left="1148" Top="315" Width="45"/>
        <DisablePainted Valor="false"/>
        <Texto>ano</Texto>
        <Observacao/>
        <Dicionario/>
        <Fonte Estilo="1" Nome="Arial" Tamanho="12"/>
        <Ancorado Valor="false"/>
        <DirecaoFromInspector Valor="0"/>
        <Autosize Valor="true"/>
        <Identificador Valor="false"/>
        <Opcional Valor="false"/>
        <Multivalorado Valor="false"/>
        <CardMinFromString Valor="1"/>
        <CardMaxFromString Valor="n"/>
        <TipoAtributo Valor=""/>
    </Atributo>
    <Ligacao ID="105">
        <DisablePainted Valor="false"/>
        <Tag LinhaMestre="-1"/>
        <Dashed Valor="false"/>
        <Ancorado Valor="false"/>
        <TemSetaPontaA Valor="false"/>
        <TemSetaPontaB Valor="false"/>
        <SetaAberta Valor="true"/>
        <SetaLargura Valor="10"/>
        <Inteligente Valor="true"/>
        <Largura Valor="1"/>
        <Ligacoes PontaA="104" PontaB="79"/>
        <Pontos>
            <Ponto Left="1144" Top="319"/>
            <Ponto Left="1135" Top="319"/>
            <Ponto Left="1135" Top="355"/>
            <Ponto Left="1135" Top="355"/>
            <Ponto Left="1135" Top="383"/>
        </Pontos>
    </Ligacao>
    <Entidade ID="117">
        <Bounds Height="58" Left="1585" Top="387" Width="120"/>
        <DisablePainted Valor="false"/>
        <Texto>Seguradora</Texto>
        <Observacao/>
        <Dicionario/>
        <Fonte Estilo="1" Nome="Arial" Tamanho="12"/>
        <Ancorado Valor="false"/>
        <AtributosOcultos Valor=""/>
    </Entidade>
    <Relacionamento ID="191">
        <Bounds Height="50" Left="818" Top="391" Width="150"/>
        <DisablePainted Valor="false"/>
        <Texto>Possui</Texto>
        <Observacao/>
        <Dicionario/>
        <Fonte Estilo="1" Nome="Arial" Tamanho="12"/>
        <Ancorado Valor="false"/>
    </Relacionamento>
    <Ligacao ID="194">
        <DisablePainted Valor="false"/>
        <Tag LinhaMestre="-1"/>
        <Dashed Valor="false"/>
        <Ancorado Valor="false"/>
        <TemSetaPontaA Valor="false"/>
        <TemSetaPontaB Valor="false"/>
        <SetaAberta Valor="true"/>
        <SetaLargura Valor="10"/>
        <Inteligente Valor="true"/>
        <Largura Valor="1"/>
        <Ligacoes PontaA="191" PontaB="58"/>
        <Pontos>
            <Ponto Left="815" Top="413"/>
            <Ponto Left="766" Top="413"/>
            <Ponto Left="766" Top="413"/>
            <Ponto Left="717" Top="413"/>
        </Pontos>
        <Cardinalidade ID="195">
            <Bounds Height="15" Left="727" Top="400" Width="35"/>
            <DisablePainted Valor="false"/>
            <Texto>Cardinalidade_3</Texto>
            <Observacao/>
            <Dicionario/>
            <Fonte Estilo="1" Nome="Arial" Tamanho="12"/>
            <Ancorado Valor="false"/>
            <TamanhoAutmatico Valor="true"/>
            <Card Valor="0"/>
            <MovimentacaoManual Valor="false"/>
            <Papel Valor=""/>
        </Cardinalidade>
    </Ligacao>
    <Ligacao ID="197">
        <DisablePainted Valor="false"/>
        <Tag LinhaMestre="-1"/>
        <Dashed Valor="false"/>
        <Ancorado Valor="false"/>
        <TemSetaPontaA Valor="false"/>
        <TemSetaPontaB Valor="false"/>
        <SetaAberta Valor="true"/>
        <SetaLargura Valor="10"/>
        <Inteligente Valor="true"/>
        <Largura Valor="1"/>
        <Ligacoes PontaA="191" PontaB="79"/>
        <Pontos>
            <Ponto Left="965" Top="413"/>
            <Ponto Left="1008" Top="413"/>
            <Ponto Left="1008" Top="414"/>
            <Ponto Left="1050" Top="414"/>
        </Pontos>
        <Cardinalidade ID="198">
            <Bounds Height="15" Left="1010" Top="401" Width="36"/>
            <DisablePainted Valor="false"/>
            <Texto>Cardinalidade_4</Texto>
            <Observacao/>
            <Dicionario/>
            <Fonte Estilo="1" Nome="Arial" Tamanho="12"/>
            <Ancorado Valor="false"/>
            <TamanhoAutmatico Valor="true"/>
            <Card Valor="2"/>
            <MovimentacaoManual Valor="false"/>
            <Papel Valor=""/>
        </Cardinalidade>
    </Ligacao>
    <Relacionamento ID="202">
        <Bounds Height="50" Left="1313" Top="392" Width="150"/>
        <DisablePainted Valor="false"/>
        <Texto>É assegurado</Texto>
        <Observacao/>
        <Dicionario/>
        <Fonte Estilo="1" Nome="Arial" Tamanho="12"/>
        <Ancorado Valor="false"/>
    </Relacionamento>
    <Ligacao ID="204">
        <DisablePainted Valor="false"/>
        <Tag LinhaMestre="-1"/>
        <Dashed Valor="false"/>
        <Ancorado Valor="false"/>
        <TemSetaPontaA Valor="false"/>
        <TemSetaPontaB Valor="false"/>
        <SetaAberta Valor="true"/>
        <SetaLargura Valor="10"/>
        <Inteligente Valor="true"/>
        <Largura Valor="1"/>
        <Ligacoes PontaA="202" PontaB="79"/>
        <Pontos>
            <Ponto Left="1310" Top="414"/>
            <Ponto Left="1240" Top="414"/>
            <Ponto Left="1240" Top="413"/>
            <Ponto Left="1171" Top="413"/>
        </Pontos>
        <Cardinalidade ID="205">
            <Bounds Height="15" Left="1181" Top="400" Width="36"/>
            <DisablePainted Valor="false"/>
            <Texto>Cardinalidade_5</Texto>
            <Observacao/>
            <Dicionario/>
            <Fonte Estilo="1" Nome="Arial" Tamanho="12"/>
            <Ancorado Valor="false"/>
            <TamanhoAutmatico Valor="true"/>
            <Card Valor="2"/>
            <MovimentacaoManual Valor="false"/>
            <Papel Valor=""/>
        </Cardinalidade>
    </Ligacao>
    <Ligacao ID="206">
        <DisablePainted Valor="false"/>
        <Tag LinhaMestre="-1"/>
        <Dashed Valor="false"/>
        <Ancorado Valor="false"/>
        <TemSetaPontaA Valor="false"/>
        <TemSetaPontaB Valor="false"/>
        <SetaAberta Valor="true"/>
        <SetaLargura Valor="10"/>
        <Inteligente Valor="true"/>
        <Largura Valor="1"/>
        <Ligacoes PontaA="202" PontaB="117"/>
        <Pontos>
            <Ponto Left="1460" Top="414"/>
            <Ponto Left="1521" Top="414"/>
            <Ponto Left="1521" Top="414"/>
            <Ponto Left="1581" Top="414"/>
        </Pontos>
        <Cardinalidade ID="207">
            <Bounds Height="15" Left="1542" Top="401" Width="35"/>
            <DisablePainted Valor="false"/>
            <Texto>Cardinalidade_6</Texto>
            <Observacao/>
            <Dicionario/>
            <Fonte Estilo="1" Nome="Arial" Tamanho="12"/>
            <Ancorado Valor="false"/>
            <TamanhoAutmatico Valor="true"/>
            <Card Valor="1"/>
            <MovimentacaoManual Valor="false"/>
            <Papel Valor=""/>
        </Cardinalidade>
    </Ligacao>
    <Atributo ID="281">
        <Bounds Height="14" Left="1162" Top="334" Width="99"/>
        <DisablePainted Valor="false"/>
        <Texto>data_compra</Texto>
        <Observacao/>
        <Dicionario/>
        <Fonte Estilo="1" Nome="Arial" Tamanho="12"/>
        <Ancorado Valor="false"/>
        <DirecaoFromInspector Valor="0"/>
        <Autosize Valor="true"/>
        <Identificador Valor="false"/>
        <Opcional Valor="false"/>
        <Multivalorado Valor="false"/>
        <CardMinFromString Valor="1"/>
        <CardMaxFromString Valor="n"/>
        <TipoAtributo Valor=""/>
    </Atributo>
    <Ligacao ID="282">
        <DisablePainted Valor="false"/>
        <Tag LinhaMestre="-1"/>
        <Dashed Valor="false"/>
        <Ancorado Valor="false"/>
        <TemSetaPontaA Valor="false"/>
        <TemSetaPontaB Valor="false"/>
        <SetaAberta Valor="true"/>
        <SetaLargura Valor="10"/>
        <Inteligente Valor="true"/>
        <Largura Valor="1"/>
        <Ligacoes PontaA="281" PontaB="79"/>
        <Pontos>
            <Ponto Left="1158" Top="338"/>
            <Ponto Left="1149" Top="338"/>
            <Ponto Left="1149" Top="364"/>
            <Ponto Left="1149" Top="364"/>
            <Ponto Left="1149" Top="383"/>
        </Pontos>
    </Ligacao>
    <Atributo ID="284">
        <Bounds Height="14" Left="1176" Top="353" Width="46"/>
        <DisablePainted Valor="false"/>
        <Texto>tipo</Texto>
        <Observacao/>
        <Dicionario/>
        <Fonte Estilo="1" Nome="Arial" Tamanho="12"/>
        <Ancorado Valor="false"/>
        <DirecaoFromInspector Valor="0"/>
        <Autosize Valor="true"/>
        <Identificador Valor="false"/>
        <Opcional Valor="false"/>
        <Multivalorado Valor="false"/>
        <CardMinFromString Valor="1"/>
        <CardMaxFromString Valor="n"/>
        <TipoAtributo Valor="char ('M', 'F')"/>
    </Atributo>
    <Ligacao ID="285">
        <DisablePainted Valor="false"/>
        <Tag LinhaMestre="-1"/>
        <Dashed Valor="false"/>
        <Ancorado Valor="false"/>
        <TemSetaPontaA Valor="false"/>
        <TemSetaPontaB Valor="false"/>
        <SetaAberta Valor="true"/>
        <SetaLargura Valor="10"/>
        <Inteligente Valor="true"/>
        <Largura Valor="1"/>
        <Ligacoes PontaA="284" PontaB="79"/>
        <Pontos>
            <Ponto Left="1172" Top="357"/>
            <Ponto Left="1163" Top="357"/>
            <Ponto Left="1163" Top="383"/>
        </Pontos>
    </Ligacao>
    <Entidade ID="425">
        <Bounds Height="58" Left="499" Top="694" Width="120"/>
        <DisablePainted Valor="false"/>
        <Texto>Corrida</Texto>
        <Observacao/>
        <Dicionario/>
        <Fonte Estilo="1" Nome="Arial" Tamanho="12"/>
        <Ancorado Valor="false"/>
        <AtributosOcultos Valor=""/>
    </Entidade>
    <Ligacao ID="428">
        <DisablePainted Valor="false"/>
        <Tag LinhaMestre="-1"/>
        <Dashed Valor="false"/>
        <Ancorado Valor="false"/>
        <TemSetaPontaA Valor="false"/>
        <TemSetaPontaB Valor="false"/>
        <SetaAberta Valor="true"/>
        <SetaLargura Valor="10"/>
        <Inteligente Valor="true"/>
        <Largura Valor="1"/>
        <Ligacoes PontaA="432" PontaB="-1"/>
        <Pontos>
            <Ponto Left="549" Top="852"/>
            <Ponto Left="527" Top="852"/>
            <Ponto Left="527" Top="749"/>
        </Pontos>
    </Ligacao>
    <Ligacao ID="429">
        <DisablePainted Valor="false"/>
        <Tag LinhaMestre="-1"/>
        <Dashed Valor="false"/>
        <Ancorado Valor="false"/>
        <TemSetaPontaA Valor="false"/>
        <TemSetaPontaB Valor="false"/>
        <SetaAberta Valor="true"/>
        <SetaLargura Valor="10"/>
        <Inteligente Valor="true"/>
        <Largura Valor="1"/>
        <Ligacoes PontaA="433" PontaB="-1"/>
        <Pontos>
            <Ponto Left="560" Top="834"/>
            <Ponto Left="541" Top="834"/>
            <Ponto Left="541" Top="749"/>
        </Pontos>
    </Ligacao>
    <Ligacao ID="430">
        <DisablePainted Valor="false"/>
        <Tag LinhaMestre="-1"/>
        <Dashed Valor="false"/>
        <Ancorado Valor="false"/>
        <TemSetaPontaA Valor="false"/>
        <TemSetaPontaB Valor="false"/>
        <SetaAberta Valor="true"/>
        <SetaLargura Valor="10"/>
        <Inteligente Valor="true"/>
        <Largura Valor="1"/>
        <Ligacoes PontaA="435" PontaB="-1"/>
        <Pontos>
            <Ponto Left="576" Top="816"/>
            <Ponto Left="552" Top="816"/>
            <Ponto Left="552" Top="749"/>
        </Pontos>
    </Ligacao>
    <Ligacao ID="431">
        <DisablePainted Valor="false"/>
        <Tag LinhaMestre="-1"/>
        <Dashed Valor="false"/>
        <Ancorado Valor="false"/>
        <TemSetaPontaA Valor="false"/>
        <TemSetaPontaB Valor="false"/>
        <SetaAberta Valor="true"/>
        <SetaLargura Valor="10"/>
        <Inteligente Valor="true"/>
        <Largura Valor="1"/>
        <Ligacoes PontaA="437" PontaB="-1"/>
        <Pontos>
            <Ponto Left="583" Top="796"/>
            <Ponto Left="567" Top="796"/>
            <Ponto Left="567" Top="749"/>
        </Pontos>
    </Ligacao>
    <Atributo ID="432">
        <Bounds Height="14" Left="552" Top="848" Width="83"/>
        <DisablePainted Valor="false"/>
        <Texto>valor_total</Texto>
        <Observacao/>
        <Dicionario/>
        <Fonte Estilo="1" Nome="Arial" Tamanho="12"/>
        <Ancorado Valor="false"/>
        <DirecaoFromInspector Valor="0"/>
        <Autosize Valor="true"/>
        <Identificador Valor="false"/>
        <Opcional Valor="false"/>
        <Multivalorado Valor="false"/>
        <CardMinFromString Valor="1"/>
        <CardMaxFromString Valor="n"/>
        <TipoAtributo Valor=""/>
    </Atributo>
    <Atributo ID="433">
        <Bounds Height="14" Left="564" Top="830" Width="106"/>
        <DisablePainted Valor="false"/>
        <Texto>data_hora_fim</Texto>
        <Observacao/>
        <Dicionario/>
        <Fonte Estilo="1" Nome="Arial" Tamanho="12"/>
        <Ancorado Valor="false"/>
        <DirecaoFromInspector Valor="0"/>
        <Autosize Valor="true"/>
        <Identificador Valor="false"/>
        <Opcional Valor="false"/>
        <Multivalorado Valor="false"/>
        <CardMinFromString Valor="1"/>
        <CardMaxFromString Valor="n"/>
        <TipoAtributo Valor=""/>
    </Atributo>
    <Atributo ID="435">
        <Bounds Height="14" Left="580" Top="812" Width="122"/>
        <DisablePainted Valor="false"/>
        <Texto>data_hora_inicio</Texto>
        <Observacao/>
        <Dicionario/>
        <Fonte Estilo="1" Nome="Arial" Tamanho="12"/>
        <Ancorado Valor="false"/>
        <DirecaoFromInspector Valor="0"/>
        <Autosize Valor="true"/>
        <Identificador Valor="false"/>
        <Opcional Valor="false"/>
        <Multivalorado Valor="false"/>
        <CardMinFromString Valor="1"/>
        <CardMaxFromString Valor="n"/>
        <TipoAtributo Valor=""/>
    </Atributo>
    <Ligacao ID="436">
        <DisablePainted Valor="false"/>
        <Tag LinhaMestre="-1"/>
        <Dashed Valor="false"/>
        <Ancorado Valor="false"/>
        <TemSetaPontaA Valor="false"/>
        <TemSetaPontaB Valor="false"/>
        <SetaAberta Valor="true"/>
        <SetaLargura Valor="10"/>
        <Inteligente Valor="true"/>
        <Largura Valor="1"/>
        <Ligacoes PontaA="438" PontaB="-1"/>
        <Pontos>
            <Ponto Left="593" Top="777"/>
            <Ponto Left="584" Top="777"/>
            <Ponto Left="584" Top="759"/>
            <Ponto Left="584" Top="759"/>
            <Ponto Left="584" Top="759"/>
            <Ponto Left="584" Top="749"/>
        </Pontos>
    </Ligacao>
    <Atributo ID="437">
        <Bounds Height="14" Left="587" Top="792" Width="130"/>
        <DisablePainted Valor="false"/>
        <Texto>endereço_destino</Texto>
        <Observacao/>
        <Dicionario/>
        <Fonte Estilo="1" Nome="Arial" Tamanho="12"/>
        <Ancorado Valor="false"/>
        <DirecaoFromInspector Valor="0"/>
        <Autosize Valor="true"/>
        <Identificador Valor="false"/>
        <Opcional Valor="false"/>
        <Multivalorado Valor="false"/>
        <CardMinFromString Valor="1"/>
        <CardMaxFromString Valor="n"/>
        <TipoAtributo Valor=""/>
    </Atributo>
    <Atributo ID="438">
        <Bounds Height="14" Left="597" Top="773" Width="114"/>
        <DisablePainted Valor="false"/>
        <Texto>nro_sequencial</Texto>
        <Observacao/>
        <Dicionario/>
        <Fonte Estilo="1" Nome="Arial" Tamanho="12"/>
        <Ancorado Valor="false"/>
        <DirecaoFromInspector Valor="0"/>
        <Autosize Valor="true"/>
        <Identificador Valor="true"/>
        <Opcional Valor="false"/>
        <Multivalorado Valor="false"/>
        <CardMinFromString Valor="1"/>
        <CardMaxFromString Valor="n"/>
        <TipoAtributo Valor=""/>
    </Atributo>
    <EntidadeAssociativa ID="474">
        <Bounds Height="58" Left="141" Top="696" Width="158"/>
        <DisablePainted Valor="false"/>
        <Texto>ACQ</Texto>
        <Observacao/>
        <Dicionario/>
        <Fonte Estilo="1" Nome="Arial" Tamanho="12"/>
        <Ancorado Valor="false"/>
        <AtributosOcultos Valor=""/>
        <Relacionamento ID="473">
            <DisablePainted Valor="false"/>
            <Texto>Atendimento</Texto>
            <Observacao/>
            <Dicionario/>
            <Fonte Estilo="1" Nome="Arial" Tamanho="12"/>
            <Ancorado Valor="false"/>
        </Relacionamento>
    </EntidadeAssociativa>
    <Ligacao ID="478">
        <DisablePainted Valor="false"/>
        <Tag LinhaMestre="-1"/>
        <Dashed Valor="false"/>
        <Ancorado Valor="false"/>
        <TemSetaPontaA Valor="false"/>
        <TemSetaPontaB Valor="false"/>
        <SetaAberta Valor="true"/>
        <SetaLargura Valor="10"/>
        <Inteligente Valor="true"/>
        <Largura Valor="1"/>
        <Ligacoes PontaA="473" PontaB="24"/>
        <Pontos>
            <Ponto Left="216" Top="701"/>
            <Ponto Left="216" Top="567"/>
            <Ponto Left="216" Top="567"/>
            <Ponto Left="216" Top="441"/>
        </Pontos>
        <Cardinalidade ID="479">
            <Bounds Height="15" Left="183" Top="451" Width="35"/>
            <DisablePainted Valor="false"/>
            <Texto>Cardinalidade_10</Texto>
            <Observacao/>
            <Dicionario/>
            <Fonte Estilo="1" Nome="Arial" Tamanho="12"/>
            <Ancorado Valor="false"/>
            <TamanhoAutmatico Valor="true"/>
            <Card Valor="0"/>
            <MovimentacaoManual Valor="false"/>
            <Papel Valor=""/>
        </Cardinalidade>
    </Ligacao>
    <Relacionamento ID="560">
        <Bounds Height="50" Left="363" Top="519" Width="150"/>
        <DisablePainted Valor="false"/>
        <Texto>Pega Carona</Texto>
        <Observacao/>
        <Dicionario/>
        <Fonte Estilo="1" Nome="Arial" Tamanho="12"/>
        <Ancorado Valor="false"/>
    </Relacionamento>
    <Ligacao ID="593">
        <DisablePainted Valor="false"/>
        <Tag LinhaMestre="-1"/>
        <Dashed Valor="false"/>
        <Ancorado Valor="false"/>
        <TemSetaPontaA Valor="false"/>
        <TemSetaPontaB Valor="false"/>
        <SetaAberta Valor="true"/>
        <SetaLargura Valor="10"/>
        <Inteligente Valor="true"/>
        <Largura Valor="1"/>
        <Ligacoes PontaA="594" PontaB="-1"/>
        <Pontos>
            <Ponto Left="1626" Top="322"/>
            <Ponto Left="1617" Top="322"/>
            <Ponto Left="1617" Top="384"/>
        </Pontos>
    </Ligacao>
    <Atributo ID="594">
        <Bounds Height="14" Left="1630" Top="318" Width="49"/>
        <DisablePainted Valor="false"/>
        <Texto>cnpj</Texto>
        <Observacao/>
        <Dicionario/>
        <Fonte Estilo="1" Nome="Arial" Tamanho="12"/>
        <Ancorado Valor="false"/>
        <DirecaoFromInspector Valor="0"/>
        <Autosize Valor="true"/>
        <Identificador Valor="true"/>
        <Opcional Valor="false"/>
        <Multivalorado Valor="false"/>
        <CardMinFromString Valor="1"/>
        <CardMaxFromString Valor="n"/>
        <TipoAtributo Valor=""/>
    </Atributo>
    <Ligacao ID="597">
        <DisablePainted Valor="false"/>
        <Tag LinhaMestre="-1"/>
        <Dashed Valor="false"/>
        <Ancorado Valor="false"/>
        <TemSetaPontaA Valor="false"/>
        <TemSetaPontaB Valor="false"/>
        <SetaAberta Valor="true"/>
        <SetaLargura Valor="10"/>
        <Inteligente Valor="true"/>
        <Largura Valor="1"/>
        <Ligacoes PontaA="598" PontaB="-1"/>
        <Pontos>
            <Ponto Left="1654" Top="360"/>
            <Ponto Left="1645" Top="360"/>
            <Ponto Left="1645" Top="384"/>
        </Pontos>
    </Ligacao>
    <Atributo ID="598">
        <Bounds Height="14" Left="1658" Top="356" Width="78"/>
        <DisablePainted Valor="false"/>
        <Texto>endereço</Texto>
        <Observacao/>
        <Dicionario/>
        <Fonte Estilo="1" Nome="Arial" Tamanho="12"/>
        <Ancorado Valor="false"/>
        <DirecaoFromInspector Valor="0"/>
        <Autosize Valor="true"/>
        <Identificador Valor="false"/>
        <Opcional Valor="false"/>
        <Multivalorado Valor="false"/>
        <CardMinFromString Valor="1"/>
        <CardMaxFromString Valor="n"/>
        <TipoAtributo Valor=""/>
    </Atributo>
    <Atributo ID="602">
        <Bounds Height="14" Left="1398" Top="463" Width="93"/>
        <DisablePainted Valor="false"/>
        <Texto>nro_apolice</Texto>
        <Observacao/>
        <Dicionario/>
        <Fonte Estilo="1" Nome="Arial" Tamanho="12"/>
        <Ancorado Valor="false"/>
        <DirecaoFromInspector Valor="0"/>
        <Autosize Valor="true"/>
        <Identificador Valor="false"/>
        <Opcional Valor="false"/>
        <Multivalorado Valor="false"/>
        <CardMinFromString Valor="1"/>
        <CardMaxFromString Valor="n"/>
        <TipoAtributo Valor=""/>
    </Atributo>
    <Ligacao ID="603">
        <DisablePainted Valor="false"/>
        <Tag LinhaMestre="-1"/>
        <Dashed Valor="false"/>
        <Ancorado Valor="false"/>
        <TemSetaPontaA Valor="false"/>
        <TemSetaPontaB Valor="false"/>
        <SetaAberta Valor="true"/>
        <SetaLargura Valor="10"/>
        <Inteligente Valor="true"/>
        <Largura Valor="1"/>
        <Ligacoes PontaA="602" PontaB="202"/>
        <Pontos>
            <Ponto Left="1394" Top="467"/>
            <Ponto Left="1385" Top="467"/>
            <Ponto Left="1385" Top="449"/>
            <Ponto Left="1385" Top="449"/>
            <Ponto Left="1385" Top="449"/>
            <Ponto Left="1385" Top="439"/>
        </Pontos>
    </Ligacao>
    <Atributo ID="605">
        <Bounds Height="14" Left="1391" Top="484" Width="101"/>
        <DisablePainted Valor="false"/>
        <Texto>valor_seguro</Texto>
        <Observacao/>
        <Dicionario/>
        <Fonte Estilo="1" Nome="Arial" Tamanho="12"/>
        <Ancorado Valor="false"/>
        <DirecaoFromInspector Valor="0"/>
        <Autosize Valor="true"/>
        <Identificador Valor="false"/>
        <Opcional Valor="false"/>
        <Multivalorado Valor="false"/>
        <CardMinFromString Valor="1"/>
        <CardMaxFromString Valor="n"/>
        <TipoAtributo Valor=""/>
    </Atributo>
    <Ligacao ID="606">
        <DisablePainted Valor="false"/>
        <Tag LinhaMestre="-1"/>
        <Dashed Valor="false"/>
        <Ancorado Valor="false"/>
        <TemSetaPontaA Valor="false"/>
        <TemSetaPontaB Valor="false"/>
        <SetaAberta Valor="true"/>
        <SetaLargura Valor="10"/>
        <Inteligente Valor="true"/>
        <Largura Valor="1"/>
        <Ligacoes PontaA="605" PontaB="202"/>
        <Pontos>
            <Ponto Left="1387" Top="488"/>
            <Ponto Left="1360" Top="488"/>
            <Ponto Left="1360" Top="431"/>
        </Pontos>
    </Ligacao>
    <Texto ID="618">
        <Bounds Height="36" Left="457" Top="256" Width="150"/>
        <DisablePainted Valor="false"/>
        <Texto>Sobreposto Total
</Texto>
        <Observacao/>
        <Fonte Estilo="1" Nome="Arial" Tamanho="12"/>
        <Ancorado Valor="false"/>
        <Titulo>Observação_1</Titulo>
        <PaintTitulo Valor="false"/>
        <Alinhamento Valor="0"/>
        <CentrarVertical Valor="false"/>
        <Tipo Valor="1"/>
        <BackColor Valor="255,255,255,255"/>
        <Sombra Valor="true"/>
        <CorSombra Valor="51,51,51,255"/>
        <Gradiente Valor="false"/>
        <GradienteStartColor Valor="0,0,0,255"/>
        <GradienteEndColor Valor="204,204,204,255"/>
        <GradientePinteDetalhe Valor="true"/>
        <GradienteCorDetalhe Valor="102,102,102,255"/>
        <GDirecao Valor="0"/>
        <Alfa Valor="80"/>
        <Autosize Valor="false"/>
        <MovimentacaoManual Valor="true"/>
    </Texto>
    <Ligacao ID="651">
        <DisablePainted Valor="false"/>
        <Tag LinhaMestre="-1"/>
        <Dashed Valor="false"/>
        <Ancorado Valor="false"/>
        <TemSetaPontaA Valor="false"/>
        <TemSetaPontaB Valor="false"/>
        <SetaAberta Valor="true"/>
        <SetaLargura Valor="10"/>
        <Inteligente Valor="true"/>
        <Largura Valor="1"/>
        <Ligacoes PontaA="473" PontaB="425"/>
        <Pontos>
            <Ponto Left="286" Top="721"/>
            <Ponto Left="396" Top="721"/>
            <Ponto Left="396" Top="721"/>
            <Ponto Left="495" Top="721"/>
        </Pontos>
        <Cardinalidade ID="652">
            <Bounds Height="15" Left="455" Top="708" Width="36"/>
            <DisablePainted Valor="false"/>
            <Texto>Cardinalidade_8</Texto>
            <Observacao/>
            <Dicionario/>
            <Fonte Estilo="1" Nome="Arial" Tamanho="12"/>
            <Ancorado Valor="false"/>
            <TamanhoAutmatico Valor="true"/>
            <Card Valor="3"/>
            <MovimentacaoManual Valor="false"/>
            <Papel Valor=""/>
        </Cardinalidade>
    </Ligacao>
    <Entidade ID="659">
        <Bounds Height="58" Left="156" Top="893" Width="120"/>
        <DisablePainted Valor="false"/>
        <Texto>Questionamento</Texto>
        <Observacao/>
        <Dicionario/>
        <Fonte Estilo="1" Nome="Arial" Tamanho="12"/>
        <Ancorado Valor="false"/>
        <AtributosOcultos Valor=""/>
    </Entidade>
    <Atributo ID="666">
        <Bounds Height="14" Left="251" Top="972" Width="114"/>
        <DisablePainted Valor="false"/>
        <Texto>nro_sequencial</Texto>
        <Observacao/>
        <Dicionario/>
        <Fonte Estilo="1" Nome="Arial" Tamanho="12"/>
        <Ancorado Valor="false"/>
        <DirecaoFromInspector Valor="0"/>
        <Autosize Valor="true"/>
        <Identificador Valor="true"/>
        <Opcional Valor="false"/>
        <Multivalorado Valor="false"/>
        <CardMinFromString Valor="1"/>
        <CardMaxFromString Valor="n"/>
        <TipoAtributo Valor=""/>
    </Atributo>
    <Ligacao ID="667">
        <DisablePainted Valor="false"/>
        <Tag LinhaMestre="-1"/>
        <Dashed Valor="false"/>
        <Ancorado Valor="false"/>
        <TemSetaPontaA Valor="false"/>
        <TemSetaPontaB Valor="false"/>
        <SetaAberta Valor="true"/>
        <SetaLargura Valor="10"/>
        <Inteligente Valor="true"/>
        <Largura Valor="1"/>
        <Ligacoes PontaA="666" PontaB="659"/>
        <Pontos>
            <Ponto Left="247" Top="976"/>
            <Ponto Left="237" Top="976"/>
            <Ponto Left="237" Top="948"/>
        </Pontos>
    </Ligacao>
    <Atributo ID="670">
        <Bounds Height="14" Left="241" Top="990" Width="77"/>
        <DisablePainted Valor="false"/>
        <Texto>pergunta</Texto>
        <Observacao/>
        <Dicionario/>
        <Fonte Estilo="1" Nome="Arial" Tamanho="12"/>
        <Ancorado Valor="false"/>
        <DirecaoFromInspector Valor="0"/>
        <Autosize Valor="true"/>
        <Identificador Valor="false"/>
        <Opcional Valor="false"/>
        <Multivalorado Valor="false"/>
        <CardMinFromString Valor="1"/>
        <CardMaxFromString Valor="n"/>
        <TipoAtributo Valor=""/>
    </Atributo>
    <Ligacao ID="671">
        <DisablePainted Valor="false"/>
        <Tag LinhaMestre="-1"/>
        <Dashed Valor="false"/>
        <Ancorado Valor="false"/>
        <TemSetaPontaA Valor="false"/>
        <TemSetaPontaB Valor="false"/>
        <SetaAberta Valor="true"/>
        <SetaLargura Valor="10"/>
        <Inteligente Valor="true"/>
        <Largura Valor="1"/>
        <Ligacoes PontaA="670" PontaB="659"/>
        <Pontos>
            <Ponto Left="237" Top="994"/>
            <Ponto Left="224" Top="994"/>
            <Ponto Left="224" Top="948"/>
        </Pontos>
    </Ligacao>
    <Atributo ID="673">
        <Bounds Height="14" Left="232" Top="1005" Width="74"/>
        <DisablePainted Valor="false"/>
        <Texto>resposta</Texto>
        <Observacao/>
        <Dicionario/>
        <Fonte Estilo="1" Nome="Arial" Tamanho="12"/>
        <Ancorado Valor="false"/>
        <DirecaoFromInspector Valor="0"/>
        <Autosize Valor="true"/>
        <Identificador Valor="false"/>
        <Opcional Valor="false"/>
        <Multivalorado Valor="false"/>
        <CardMinFromString Valor="1"/>
        <CardMaxFromString Valor="n"/>
        <TipoAtributo Valor=""/>
    </Atributo>
    <Ligacao ID="674">
        <DisablePainted Valor="false"/>
        <Tag LinhaMestre="-1"/>
        <Dashed Valor="false"/>
        <Ancorado Valor="false"/>
        <TemSetaPontaA Valor="false"/>
        <TemSetaPontaB Valor="false"/>
        <SetaAberta Valor="true"/>
        <SetaLargura Valor="10"/>
        <Inteligente Valor="true"/>
        <Largura Valor="1"/>
        <Ligacoes PontaA="673" PontaB="659"/>
        <Pontos>
            <Ponto Left="228" Top="1009"/>
            <Ponto Left="212" Top="1009"/>
            <Ponto Left="212" Top="948"/>
        </Pontos>
    </Ligacao>
    <EntidadeAssociativa ID="686">
        <Bounds Height="58" Left="618" Top="583" Width="158"/>
        <DisablePainted Valor="false"/>
        <Texto>PMC</Texto>
        <Observacao/>
        <Dicionario/>
        <Fonte Estilo="1" Nome="Arial" Tamanho="12"/>
        <Ancorado Valor="false"/>
        <AtributosOcultos Valor=""/>
        <Relacionamento ID="685">
            <DisablePainted Valor="false"/>
            <Texto>Solicitação</Texto>
            <Observacao/>
            <Dicionario/>
            <Fonte Estilo="1" Nome="Arial" Tamanho="12"/>
            <Ancorado Valor="false"/>
        </Relacionamento>
    </EntidadeAssociativa>
    <Relacionamento ID="711">
        <Bounds Height="50" Left="144" Top="809" Width="150"/>
        <DisablePainted Valor="false"/>
        <Texto>tem</Texto>
        <Observacao/>
        <Dicionario/>
        <Fonte Estilo="1" Nome="Arial" Tamanho="12"/>
        <Ancorado Valor="false"/>
    </Relacionamento>
    <Ligacao ID="718">
        <DisablePainted Valor="false"/>
        <Tag LinhaMestre="-1"/>
        <Dashed Valor="false"/>
        <Ancorado Valor="false"/>
        <TemSetaPontaA Valor="false"/>
        <TemSetaPontaB Valor="false"/>
        <SetaAberta Valor="true"/>
        <SetaLargura Valor="10"/>
        <Inteligente Valor="true"/>
        <Largura Valor="2"/>
        <Ligacoes PontaA="711" PontaB="659"/>
        <Pontos>
            <Ponto Left="216" Top="856"/>
            <Ponto Left="216" Top="873"/>
            <Ponto Left="216" Top="873"/>
            <Ponto Left="216" Top="889"/>
        </Pontos>
        <Cardinalidade ID="719">
            <Bounds Height="15" Left="182" Top="870" Width="36"/>
            <DisablePainted Valor="false"/>
            <Texto>Cardinalidade_9</Texto>
            <Observacao/>
            <Dicionario/>
            <Fonte Estilo="1" Nome="Arial" Tamanho="12"/>
            <Ancorado Valor="false"/>
            <TamanhoAutmatico Valor="true"/>
            <Card Valor="3"/>
            <MovimentacaoManual Valor="false"/>
            <Papel Valor=""/>
        </Cardinalidade>
    </Ligacao>
    <Ligacao ID="727">
        <DisablePainted Valor="false"/>
        <Tag LinhaMestre="-1"/>
        <Dashed Valor="false"/>
        <Ancorado Valor="false"/>
        <TemSetaPontaA Valor="false"/>
        <TemSetaPontaB Valor="false"/>
        <SetaAberta Valor="true"/>
        <SetaLargura Valor="10"/>
        <Inteligente Valor="true"/>
        <Largura Valor="1"/>
        <Ligacoes PontaA="711" PontaB="474"/>
        <Pontos>
            <Ponto Left="216" Top="806"/>
            <Ponto Left="216" Top="778"/>
            <Ponto Left="218" Top="778"/>
            <Ponto Left="218" Top="751"/>
        </Pontos>
        <Cardinalidade ID="728">
            <Bounds Height="15" Left="185" Top="761" Width="35"/>
            <DisablePainted Valor="false"/>
            <Texto>Cardinalidade_14</Texto>
            <Observacao/>
            <Dicionario/>
            <Fonte Estilo="1" Nome="Arial" Tamanho="12"/>
            <Ancorado Valor="false"/>
            <TamanhoAutmatico Valor="true"/>
            <Card Valor="0"/>
            <MovimentacaoManual Valor="false"/>
            <Papel Valor=""/>
        </Cardinalidade>
    </Ligacao>
    <Relacionamento ID="739">
        <Bounds Height="50" Left="627" Top="494" Width="150"/>
        <DisablePainted Valor="false"/>
        <Texto>Efetua</Texto>
        <Observacao/>
        <Dicionario/>
        <Fonte Estilo="1" Nome="Arial" Tamanho="12"/>
        <Ancorado Valor="false"/>
    </Relacionamento>
    <Ligacao ID="744">
        <DisablePainted Valor="false"/>
        <Tag LinhaMestre="-1"/>
        <Dashed Valor="false"/>
        <Ancorado Valor="false"/>
        <TemSetaPontaA Valor="false"/>
        <TemSetaPontaB Valor="false"/>
        <SetaAberta Valor="true"/>
        <SetaLargura Valor="10"/>
        <Inteligente Valor="true"/>
        <Largura Valor="1"/>
        <Ligacoes PontaA="685" PontaB="30"/>
        <Pontos>
            <Ponto Left="623" Top="608"/>
            <Ponto Left="551" Top="608"/>
            <Ponto Left="551" Top="415"/>
            <Ponto Left="487" Top="415"/>
        </Pontos>
        <Cardinalidade ID="745">
            <Bounds Height="15" Left="497" Top="402" Width="35"/>
            <DisablePainted Valor="false"/>
            <Texto>Cardinalidade_2</Texto>
            <Observacao/>
            <Dicionario/>
            <Fonte Estilo="1" Nome="Arial" Tamanho="12"/>
            <Ancorado Valor="false"/>
            <TamanhoAutmatico Valor="true"/>
            <Card Valor="0"/>
            <MovimentacaoManual Valor="false"/>
            <Papel Valor=""/>
        </Cardinalidade>
    </Ligacao>
    <Ligacao ID="748">
        <DisablePainted Valor="false"/>
        <Tag LinhaMestre="-1"/>
        <Dashed Valor="false"/>
        <Ancorado Valor="false"/>
        <TemSetaPontaA Valor="false"/>
        <TemSetaPontaB Valor="false"/>
        <SetaAberta Valor="true"/>
        <SetaLargura Valor="10"/>
        <Inteligente Valor="true"/>
        <Largura Valor="1"/>
        <Ligacoes PontaA="739" PontaB="686"/>
        <Pontos>
            <Ponto Left="699" Top="541"/>
            <Ponto Left="699" Top="560"/>
            <Ponto Left="699" Top="560"/>
            <Ponto Left="699" Top="579"/>
        </Pontos>
        <Cardinalidade ID="749">
            <Bounds Height="15" Left="665" Top="560" Width="36"/>
            <DisablePainted Valor="false"/>
            <Texto>Cardinalidade_11</Texto>
            <Observacao/>
            <Dicionario/>
            <Fonte Estilo="1" Nome="Arial" Tamanho="12"/>
            <Ancorado Valor="false"/>
            <TamanhoAutmatico Valor="true"/>
            <Card Valor="3"/>
            <MovimentacaoManual Valor="false"/>
            <Papel Valor=""/>
        </Cardinalidade>
    </Ligacao>
    <Ligacao ID="750">
        <DisablePainted Valor="false"/>
        <Tag LinhaMestre="-1"/>
        <Dashed Valor="false"/>
        <Ancorado Valor="false"/>
        <TemSetaPontaA Valor="false"/>
        <TemSetaPontaB Valor="false"/>
        <SetaAberta Valor="true"/>
        <SetaLargura Valor="10"/>
        <Inteligente Valor="true"/>
        <Largura Valor="2"/>
        <Ligacoes PontaA="685" PontaB="425"/>
        <Pontos>
            <Ponto Left="693" Top="628"/>
            <Ponto Left="693" Top="724"/>
            <Ponto Left="616" Top="724"/>
        </Pontos>
        <Cardinalidade ID="751">
            <Bounds Height="15" Left="626" Top="711" Width="36"/>
            <DisablePainted Valor="false"/>
            <Texto>Cardinalidade_12</Texto>
            <Observacao/>
            <Dicionario/>
            <Fonte Estilo="1" Nome="Arial" Tamanho="12"/>
            <Ancorado Valor="false"/>
            <TamanhoAutmatico Valor="true"/>
            <Card Valor="3"/>
            <MovimentacaoManual Valor="false"/>
            <Papel Valor=""/>
        </Cardinalidade>
    </Ligacao>
    <Ligacao ID="754">
        <DisablePainted Valor="false"/>
        <Tag LinhaMestre="-1"/>
        <Dashed Valor="false"/>
        <Ancorado Valor="false"/>
        <TemSetaPontaA Valor="false"/>
        <TemSetaPontaB Valor="false"/>
        <SetaAberta Valor="true"/>
        <SetaLargura Valor="10"/>
        <Inteligente Valor="true"/>
        <Largura Valor="1"/>
        <Ligacoes PontaA="560" PontaB="30"/>
        <Pontos>
            <Ponto Left="435" Top="516"/>
            <Ponto Left="435" Top="479"/>
            <Ponto Left="435" Top="479"/>
            <Ponto Left="435" Top="442"/>
        </Pontos>
        <Cardinalidade ID="755">
            <Bounds Height="15" Left="401" Top="452" Width="36"/>
            <DisablePainted Valor="false"/>
            <Texto>Cardinalidade_7</Texto>
            <Observacao/>
            <Dicionario/>
            <Fonte Estilo="1" Nome="Arial" Tamanho="12"/>
            <Ancorado Valor="false"/>
            <TamanhoAutmatico Valor="true"/>
            <Card Valor="3"/>
            <MovimentacaoManual Valor="false"/>
            <Papel Valor=""/>
        </Cardinalidade>
    </Ligacao>
    <Ligacao ID="758">
        <DisablePainted Valor="false"/>
        <Tag LinhaMestre="-1"/>
        <Dashed Valor="false"/>
        <Ancorado Valor="false"/>
        <TemSetaPontaA Valor="false"/>
        <TemSetaPontaB Valor="false"/>
        <SetaAberta Valor="true"/>
        <SetaLargura Valor="10"/>
        <Inteligente Valor="true"/>
        <Largura Valor="1"/>
        <Ligacoes PontaA="560" PontaB="425"/>
        <Pontos>
            <Ponto Left="435" Top="566"/>
            <Ponto Left="435" Top="628"/>
            <Ponto Left="562" Top="628"/>
            <Ponto Left="562" Top="690"/>
        </Pontos>
        <Cardinalidade ID="759">
            <Bounds Height="15" Left="528" Top="671" Width="36"/>
            <DisablePainted Valor="false"/>
            <Texto>Cardinalidade_13</Texto>
            <Observacao/>
            <Dicionario/>
            <Fonte Estilo="1" Nome="Arial" Tamanho="12"/>
            <Ancorado Valor="false"/>
            <TamanhoAutmatico Valor="true"/>
            <Card Valor="3"/>
            <MovimentacaoManual Valor="false"/>
            <Papel Valor=""/>
        </Cardinalidade>
    </Ligacao>
    <Entidade ID="761">
        <Bounds Height="58" Left="1582" Top="592" Width="120"/>
        <DisablePainted Valor="false"/>
        <Texto>Telefone</Texto>
        <Observacao/>
        <Dicionario/>
        <Fonte Estilo="1" Nome="Arial" Tamanho="12"/>
        <Ancorado Valor="false"/>
        <AtributosOcultos Valor=""/>
    </Entidade>
    <Ligacao ID="763">
        <DisablePainted Valor="false"/>
        <Tag LinhaMestre="-1"/>
        <Dashed Valor="false"/>
        <Ancorado Valor="false"/>
        <TemSetaPontaA Valor="false"/>
        <TemSetaPontaB Valor="false"/>
        <SetaAberta Valor="true"/>
        <SetaLargura Valor="10"/>
        <Inteligente Valor="true"/>
        <Largura Valor="1"/>
        <Ligacoes PontaA="764" PontaB="117"/>
        <Pontos>
            <Ponto Left="1641" Top="490"/>
            <Ponto Left="1641" Top="466"/>
            <Ponto Left="1642" Top="466"/>
            <Ponto Left="1642" Top="442"/>
        </Pontos>
        <Cardinalidade ID="765">
            <Bounds Height="15" Left="1608" Top="452" Width="35"/>
            <DisablePainted Valor="false"/>
            <Texto>Cardinalidade_15</Texto>
            <Observacao/>
            <Dicionario/>
            <Fonte Estilo="1" Nome="Arial" Tamanho="12"/>
            <Ancorado Valor="false"/>
            <TamanhoAutmatico Valor="true"/>
            <Card Valor="0"/>
            <MovimentacaoManual Valor="false"/>
            <Papel Valor=""/>
        </Cardinalidade>
    </Ligacao>
    <Relacionamento ID="764">
        <Bounds Height="50" Left="1569" Top="493" Width="150"/>
        <DisablePainted Valor="false"/>
        <Texto>tem</Texto>
        <Observacao/>
        <Dicionario/>
        <Fonte Estilo="1" Nome="Arial" Tamanho="12"/>
        <Ancorado Valor="false"/>
    </Relacionamento>
    <Ligacao ID="766">
        <DisablePainted Valor="false"/>
        <Tag LinhaMestre="-1"/>
        <Dashed Valor="false"/>
        <Ancorado Valor="false"/>
        <TemSetaPontaA Valor="false"/>
        <TemSetaPontaB Valor="false"/>
        <SetaAberta Valor="true"/>
        <SetaLargura Valor="10"/>
        <Inteligente Valor="true"/>
        <Largura Valor="2"/>
        <Ligacoes PontaA="761" PontaB="764"/>
        <Pontos>
            <Ponto Left="1642" Top="588"/>
            <Ponto Left="1642" Top="564"/>
            <Ponto Left="1641" Top="564"/>
            <Ponto Left="1641" Top="540"/>
        </Pontos>
        <Cardinalidade ID="767">
            <Bounds Height="15" Left="1608" Top="569" Width="36"/>
            <DisablePainted Valor="false"/>
            <Texto>Cardinalidade_16</Texto>
            <Observacao/>
            <Dicionario/>
            <Fonte Estilo="1" Nome="Arial" Tamanho="12"/>
            <Ancorado Valor="false"/>
            <TamanhoAutmatico Valor="true"/>
            <Card Valor="3"/>
            <MovimentacaoManual Valor="false"/>
            <Papel Valor=""/>
        </Cardinalidade>
    </Ligacao>
    <Atributo ID="771">
        <Bounds Height="14" Left="1666" Top="671" Width="69"/>
        <DisablePainted Valor="false"/>
        <Texto>numero</Texto>
        <Observacao/>
        <Dicionario/>
        <Fonte Estilo="1" Nome="Arial" Tamanho="12"/>
        <Ancorado Valor="false"/>
        <DirecaoFromInspector Valor="0"/>
        <Autosize Valor="true"/>
        <Identificador Valor="false"/>
        <Opcional Valor="false"/>
        <Multivalorado Valor="false"/>
        <CardMinFromString Valor="1"/>
        <CardMaxFromString Valor="n"/>
        <TipoAtributo Valor=""/>
    </Atributo>
    <Ligacao ID="772">
        <DisablePainted Valor="false"/>
        <Tag LinhaMestre="-1"/>
        <Dashed Valor="false"/>
        <Ancorado Valor="false"/>
        <TemSetaPontaA Valor="false"/>
        <TemSetaPontaB Valor="false"/>
        <SetaAberta Valor="true"/>
        <SetaLargura Valor="10"/>
        <Inteligente Valor="true"/>
        <Largura Valor="1"/>
        <Ligacoes PontaA="771" PontaB="761"/>
        <Pontos>
            <Ponto Left="1662" Top="675"/>
            <Ponto Left="1653" Top="675"/>
            <Ponto Left="1653" Top="657"/>
            <Ponto Left="1653" Top="657"/>
            <Ponto Left="1653" Top="657"/>
            <Ponto Left="1653" Top="647"/>
        </Pontos>
    </Ligacao>
    <Atributo ID="774">
        <Bounds Height="14" Left="1644" Top="340" Width="55"/>
        <DisablePainted Valor="false"/>
        <Texto>nome</Texto>
        <Observacao/>
        <Dicionario/>
        <Fonte Estilo="1" Nome="Arial" Tamanho="12"/>
        <Ancorado Valor="false"/>
        <DirecaoFromInspector Valor="0"/>
        <Autosize Valor="true"/>
        <Identificador Valor="false"/>
        <Opcional Valor="false"/>
        <Multivalorado Valor="false"/>
        <CardMinFromString Valor="1"/>
        <CardMaxFromString Valor="n"/>
        <TipoAtributo Valor=""/>
    </Atributo>
    <Ligacao ID="775">
        <DisablePainted Valor="false"/>
        <Tag LinhaMestre="-1"/>
        <Dashed Valor="false"/>
        <Ancorado Valor="false"/>
        <TemSetaPontaA Valor="false"/>
        <TemSetaPontaB Valor="false"/>
        <SetaAberta Valor="true"/>
        <SetaLargura Valor="10"/>
        <Inteligente Valor="true"/>
        <Largura Valor="1"/>
        <Ligacoes PontaA="774" PontaB="117"/>
        <Pontos>
            <Ponto Left="1640" Top="344"/>
            <Ponto Left="1631" Top="344"/>
            <Ponto Left="1631" Top="367"/>
            <Ponto Left="1631" Top="367"/>
            <Ponto Left="1631" Top="383"/>
        </Pontos>
    </Ligacao>
    <Atributo ID="784">
        <Bounds Height="14" Left="273" Top="538" Width="51"/>
        <DisablePainted Valor="false"/>
        <Texto>valor</Texto>
        <Observacao/>
        <Dicionario/>
        <Fonte Estilo="1" Nome="Arial" Tamanho="12"/>
        <Ancorado Valor="false"/>
        <DirecaoFromInspector Valor="1"/>
        <Autosize Valor="true"/>
        <Identificador Valor="false"/>
        <Opcional Valor="false"/>
        <Multivalorado Valor="false"/>
        <CardMinFromString Valor="1"/>
        <CardMaxFromString Valor="n"/>
        <TipoAtributo Valor=""/>
    </Atributo>
    <Ligacao ID="785">
        <DisablePainted Valor="false"/>
        <Tag LinhaMestre="-1"/>
        <Dashed Valor="false"/>
        <Ancorado Valor="false"/>
        <TemSetaPontaA Valor="false"/>
        <TemSetaPontaB Valor="false"/>
        <SetaAberta Valor="true"/>
        <SetaLargura Valor="10"/>
        <Inteligente Valor="true"/>
        <Largura Valor="1"/>
        <Ligacoes PontaA="560" PontaB="784"/>
        <Pontos>
            <Ponto Left="360" Top="541"/>
            <Ponto Left="340" Top="541"/>
            <Ponto Left="340" Top="542"/>
            <Ponto Left="322" Top="542"/>
        </Pontos>
    </Ligacao>
    <Atributo ID="789">
        <Bounds Height="14" Left="836" Top="598" Width="51"/>
        <DisablePainted Valor="false"/>
        <Texto>valor</Texto>
        <Observacao/>
        <Dicionario/>
        <Fonte Estilo="1" Nome="Arial" Tamanho="12"/>
        <Ancorado Valor="false"/>
        <DirecaoFromInspector Valor="0"/>
        <Autosize Valor="true"/>
        <Identificador Valor="false"/>
        <Opcional Valor="false"/>
        <Multivalorado Valor="false"/>
        <CardMinFromString Valor="1"/>
        <CardMaxFromString Valor="n"/>
        <TipoAtributo Valor=""/>
    </Atributo>
    <Ligacao ID="790">
        <DisablePainted Valor="false"/>
        <Tag LinhaMestre="-1"/>
        <Dashed Valor="false"/>
        <Ancorado Valor="false"/>
        <TemSetaPontaA Valor="false"/>
        <TemSetaPontaB Valor="false"/>
        <SetaAberta Valor="true"/>
        <SetaLargura Valor="10"/>
        <Inteligente Valor="true"/>
        <Largura Valor="1"/>
        <Ligacoes PontaA="789" PontaB="685"/>
        <Pontos>
            <Ponto Left="832" Top="602"/>
            <Ponto Left="803" Top="602"/>
            <Ponto Left="803" Top="602"/>
            <Ponto Left="740" Top="602"/>
        </Pontos>
    </Ligacao>
    <Ligacao ID="795">
        <DisablePainted Valor="false"/>
        <Tag LinhaMestre="-1"/>
        <Dashed Valor="false"/>
        <Ancorado Valor="false"/>
        <TemSetaPontaA Valor="false"/>
        <TemSetaPontaB Valor="false"/>
        <SetaAberta Valor="true"/>
        <SetaLargura Valor="10"/>
        <Inteligente Valor="true"/>
        <Largura Valor="1"/>
        <Ligacoes PontaA="739" PontaB="58"/>
        <Pontos>
            <Ponto Left="699" Top="491"/>
            <Ponto Left="699" Top="466"/>
            <Ponto Left="699" Top="466"/>
            <Ponto Left="699" Top="441"/>
        </Pontos>
        <Cardinalidade ID="796">
            <Bounds Height="15" Left="665" Top="451" Width="36"/>
            <DisablePainted Valor="false"/>
            <Texto>Cardinalidade_1</Texto>
            <Observacao/>
            <Dicionario/>
            <Fonte Estilo="1" Nome="Arial" Tamanho="12"/>
            <Ancorado Valor="false"/>
            <TamanhoAutmatico Valor="true"/>
            <Card Valor="3"/>
            <MovimentacaoManual Valor="false"/>
            <Papel Valor=""/>
        </Cardinalidade>
    </Ligacao>
</DIAGRAMA>
